async_siril/__init__.py
async_siril/command.py
async_siril/command_types.py
async_siril/conversion_file.py
async_siril/event.py
async_siril/helpers.py
async_siril/resources.py
async_siril/siril.py
async_siril/system.py
async_siril-0.4.0.dist-info/METADATA
async_siril-0.4.0.dist-info/WHEEL
async_siril-0.4.0.dist-info/licenses/LICENSE
async_siril-0.4.0.dist-info/RECORD
