Metadata-Version: 2.4
Name: async-siril
Version: 0.4.0
Summary: Python async wrapper around Siril astrophotography software.
Project-URL: Homepage, https://github.com/KyleLeNeau/async-siril
Author: Kyle LeNeau
License-Expression: BSD-3-Clause
License-File: LICENSE
Classifier: Environment :: Console
Classifier: Intended Audience :: Developers
Classifier: Intended Audience :: Science/Research
Classifier: License :: OSI Approved :: BSD License
Classifier: Operating System :: OS Independent
Classifier: Programming Language :: Python :: 3 :: Only
Classifier: Programming Language :: Python :: 3.12
Classifier: Programming Language :: Python :: 3.13
Requires-Python: >=3.12
Requires-Dist: asyncio>=3.4.3
Requires-Dist: psutil>=7.0.0
Requires-Dist: structlog>=25.4.0
